Metadata-Version: 2.1
Name: lxml-to-dict-total
Version: 1.0.0
Summary: A simple conversion of an lxml.objectify element to a python dictionary.
Home-page: https://github.com/admelix/lxml_to_dict
Author: Jose Sakuda
Author-email: sakudacastro@gmail.com
License: MPL-2.0 license
License-File: LICENSE
